tno.mpc.mpyc.exponentiation-1.6.2-py3.8-nspkg.pth
tno/mpc/mpyc/exponentiation/__init__.py
tno/mpc/mpyc/exponentiation/exponent.py
tno/mpc/mpyc/exponentiation/precision_ledger.py
tno/mpc/mpyc/exponentiation/py.typed
tno/mpc/mpyc/exponentiation/utils.py
tno/mpc/mpyc/exponentiation/test/__init__.py
tno/mpc/mpyc/exponentiation/test/test_exponent.py
tno.mpc.mpyc.exponentiation-1.6.2.dist-info/LICENSE
tno.mpc.mpyc.exponentiation-1.6.2.dist-info/METADATA
tno.mpc.mpyc.exponentiation-1.6.2.dist-info/WHEEL
tno.mpc.mpyc.exponentiation-1.6.2.dist-info/namespace_packages.txt
tno.mpc.mpyc.exponentiation-1.6.2.dist-info/top_level.txt
tno.mpc.mpyc.exponentiation-1.6.2.dist-info/RECORD
