Metadata-Version: 2.1
Name: tno.mpc.mpyc.exponentiation
Version: 1.6.2
Summary: A generic extension to MPyC that allows you to securely compute a^[x], where a is a non-negative, plain-text base (floating point or integer) and x is a secure number (SecFxp or SecInt)
Home-page: https://mpc.tno.nl/
Author: TNO MPC Lab
Author-email: mpclab@tno.nl
Maintainer: TNO MPC Lab
Maintainer-email: mpclab@tno.nl
License: Apache License, Version 2.0
Download-URL: https://pypi.org/project/tno.mpc.mpyc.exponentiation/#files
Project-URL: Documentation, https://docs.mpc.tno.nl/mpyc/exponentiation/1.6.2
Project-URL: Source Code, https://github.com/TNO-MPC/mpyc.exponentiation
Keywords: TNO,MPC,multi-party computation,MPyC,exponentiation
Platform: any
Classifier: License :: OSI Approved :: Apache Software License
Classifier: Programming Language :: Python :: 3
Classifier: Operating System :: OS Independent
Classifier: Intended Audience :: Developers
Classifier: Intended Audience :: Information Technology
Classifier: Intended Audience :: Science/Research
Classifier: Typing :: Typed
Classifier: Topic :: Security :: Cryptography
License-File: LICENSE
Requires-Dist: tno.mpc.mpyc.stubs (>=0.3.0)
Requires-Dist: mpyc (>=0.6.8)
Provides-Extra: gmpy
Requires-Dist: gmpy2 (>=2.1.0) ; extra == 'gmpy'
Provides-Extra: tests
Requires-Dist: pytest ; extra == 'tests'
Requires-Dist: pytest-asyncio ; extra == 'tests'
